alleycat/ui/__init__.py
alleycat/ui/blender.py
alleycat/ui/bounded.py
alleycat/ui/button.py
alleycat/ui/canvas.py
alleycat/ui/common.py
alleycat/ui/component.py
alleycat/ui/container.py
alleycat/ui/context.py
alleycat/ui/context_aware.py
alleycat/ui/drawable.py
alleycat/ui/error.py
alleycat/ui/event.py
alleycat/ui/font.py
alleycat/ui/frame.py
alleycat/ui/glass.py
alleycat/ui/image.py
alleycat/ui/input.py
alleycat/ui/keyboard.py
alleycat/ui/label.py
alleycat/ui/laf.py
alleycat/ui/mouse.py
alleycat/ui/overlay.py
alleycat/ui/panel.py
alleycat/ui/registry.py
alleycat/ui/style.py
alleycat/ui/toolkit.py
alleycat/ui/window.py
alleycat/ui/layout/__init__.py
alleycat/ui/layout/absolute.py
alleycat/ui/layout/anchor.py
alleycat/ui/layout/border.py
alleycat/ui/layout/box.py
alleycat/ui/layout/layout.py
alleycat/ui/layout/stack.py
alleycat_ui-0.0.5.dist-info/LICENSE
alleycat_ui-0.0.5.dist-info/METADATA
alleycat_ui-0.0.5.dist-info/WHEEL
alleycat_ui-0.0.5.dist-info/top_level.txt
alleycat_ui-0.0.5.dist-info/RECORD
