Metadata-Version: 2.1
Name: alleycat-ui
Version: 0.0.5
Summary: Lightweight GUI widget toolkit for UPBGE (Uchronia Project Blender Game Engine).
Home-page: https://github.com/mysticfall/alleycat-ui
Author: Xavier Cho
Author-email: mysticfallband@gmail.com
License: UNKNOWN
Platform: UNKNOWN
Classifier: Programming Language :: Python :: 3
Classifier: License :: OSI Approved :: GNU General Public License v3 or later (GPLv3+)
Classifier: Operating System :: OS Independent
Requires-Dist: alleycat-reactive (==0.4.7)
Requires-Dist: returns (==0.15.0)
Requires-Dist: rx (==3.1.1)
Requires-Dist: pangocairocffi (==0.5.0)
